aiosubstrate/__init__.py
aiosubstrate/base.py
aiosubstrate/constants.py
aiosubstrate/contracts.py
aiosubstrate/exceptions.py
aiosubstrate/extensions.py
aiosubstrate/interfaces.py
aiosubstrate/key.py
aiosubstrate/keypair.py
aiosubstrate/py.typed
aiosubstrate/storage.py
aiosubstrate/utils/__init__.py
aiosubstrate/utils/caching.py
aiosubstrate/utils/ecdsa_helpers.py
aiosubstrate/utils/encrypted_json.py
aiosubstrate/utils/hasher.py
aiosubstrate/utils/ss58.py
aiosubstrate-0.1.1.dist-info/METADATA
aiosubstrate-0.1.1.dist-info/WHEEL
aiosubstrate-0.1.1.dist-info/top_level.txt
aiosubstrate-0.1.1.dist-info/RECORD
