Metadata-Version: 2.4
Name: aiosubstrate
Version: 0.1.1
Summary: A library for interacting with Substrate node (py-substrate-interface fork)
Author-email: "Stichting Polkascan (Polkascan Foundation)" <info@polkascan.org>
Maintainer-email: Lev Gorodetskii <github@drsr.io>
Project-URL: Homepage, https://github.com/dipdup-io/aiosubstrate
Keywords: interface,polkascan,polkadot,substrate,blockchain,rpc,kusama
Classifier: Development Status :: 4 - Beta
Classifier: Intended Audience :: Developers
Classifier: License :: OSI Approved :: Apache Software License
Classifier: Operating System :: POSIX :: Linux
Classifier: Operating System :: MacOS :: MacOS X
Classifier: Programming Language :: Python :: 3
Classifier: Programming Language :: Python :: 3.10
Classifier: Programming Language :: Python :: 3.11
Classifier: Programming Language :: Python :: 3.12
Classifier: Topic :: Software Development :: Libraries
Classifier: Typing :: Typed
Requires-Python: <3.13,>=3.10
Requires-Dist: aiohttp>=3.11.6
Requires-Dist: scalecodec>=1.2.11
Requires-Dist: xxhash>=3.5.0
Requires-Dist: websocket-client>=1.8.0
Requires-Dist: orjson>=3.10.12
Provides-Extra: full
Requires-Dist: base58>=2.1.1; extra == "full"
Requires-Dist: certifi>=2024.8.30; extra == "full"
Requires-Dist: ecdsa>=0.19.0; extra == "full"
Requires-Dist: eth-keys>=0.6.0; extra == "full"
Requires-Dist: eth-utils>=5.1.0; extra == "full"
Requires-Dist: idna>=3.10; extra == "full"
Requires-Dist: py-bip39-bindings>=0.1.12; extra == "full"
Requires-Dist: py-ed25519-zebra-bindings>=1.1.0; extra == "full"
Requires-Dist: py-sr25519-bindings>=0.2.1; extra == "full"
Requires-Dist: pycryptodome>=3.21.0; extra == "full"
Requires-Dist: pynacl>=1.5.0; extra == "full"
